{
  "id": 111,
  "slug": "campionato-italiano-a-squadre-cis-2016",
  "title": "Campionato Italiano a Squadre CIS 2016",
  "body": "Il campionato a squadre 2016, per la serie A1 girone 1, la serie A2 girone 1, serie C girone 3 e la Promozione Liguria gironi 1,2 e 3, si svolgerà nei giorni 11-12-13 marzo a Santa Margherita Ligure presso la Palestra dell'Istituto Comprensivo V.G. Rossi in via Generale Liuzzi, 2. ([abbinamenti, squadre e classifiche](https://santasabina.altervista.org/index.php/notizie/2-non-categorizzato/110-cis-2016-informazioni))",
  "rawHtml": "\n\t\t<p><img style=\"float: left; margin: 10px 10px 20px;\" src=\"/images/documenti/torneo_cis.png\" alt=\"\" width=\"80\" height=\"50\" border=\"0\">Il campionato a squadre 2016, per la serie A1 girone 1, la serie A2 girone 1, serie C girone 3 e la Promozione Liguria gironi 1,2 e 3, si svolgerà nei giorni 11-12-13 marzo a Santa Margherita Ligure presso la Palestra dell'Istituto Comprensivo V.G. Rossi in via Generale Liuzzi, 2. (<a href=\"/index.php/notizie/2-non-categorizzato/110-cis-2016-informazioni\">abbinamenti, squadre e classifiche</a>)</p> \t"
}