{
  "id": 224,
  "slug": "torneo-sociale-autunno-2018-end",
  "title": "Torneo sociale di autunno 2018",
  "body": "Si è concluso il consueto **Torneo Sociale di autunno** che si è svolto, per sei venerdi, **dal 14 settembre al 26 ottobre**, presso i locali del Circolo. **Giorgio Costi**è il nuovo**Campione Sociale** che si è aggiudicato il torneo con **quattro punti e mezzo** punti su sei partite. Secondo, con lo stesso punteggio, **Franco Pugliese** seguito da **Paolo Nicora** con quattro punti. Primo fra gli **Under 14 Giovanni Maria Tiby** ([bando](https://santasabina.altervista.org/images/tornei/2018/2018_sociale_autunno/2018_sociale_autunno_bando.pdf), [abbinamenti e classifica](https://santasabina.altervista.org/images/tornei/2018/2018_sociale_autunno/classifica/standing.html), [fotografie](https://santasabina.altervista.org/index.php/fotografie/category/95-torneo-sociale-di-autunno-2018))",
  "rawHtml": "\n\t\t<p><img src=\"/images/documenti/torneo_sociale.png\" alt=\"\" width=\"80\" height=\"50\" style=\"margin-right: 20px; margin-bottom: 20px; float: left;\"></p>\n<p><span style=\"font-family: Calibri, sans-serif;\"><span style=\"font-size: 14.6667px;\">Si è concluso</span></span> il consueto <strong>Torneo Sociale di autunno</strong>&nbsp;che si è svolto, per sei venerdi, <strong>dal 14 settembre al 26 ottobre</strong>, presso i locali del Circolo. <strong>Giorgio Costi </strong>è il nuovo<strong> Campione Sociale</strong> che si è aggiudicato il torneo con <strong>quattro punti e mezzo</strong> punti su sei partite. Secondo, con lo stesso punteggio, <strong>Franco Pugliese</strong> seguito da <strong>Paolo Nicora</strong>&nbsp;con quattro punti. Primo fra gli <strong>Under 14 Giovanni Maria Tiby</strong> (<a href=\"/images/tornei/2018/2018_sociale_autunno/2018_sociale_autunno_bando.pdf\" target=\"_blank\" rel=\"alternate\">bando</a>, <a href=\"/images/tornei/2018/2018_sociale_autunno/classifica/standing.html\" target=\"_blank\">abbinamenti e classifica</a>, <a href=\"/index.php/fotografie/category/95-torneo-sociale-di-autunno-2018\" target=\"_self\">fotografie</a>)</p> \t"
}