{
  "id": 51,
  "slug": "3-torneo-giovanile-under-16",
  "title": "3^ Torneo giovanile Under 16",
  "body": "Domenica 6 aprile, il Circolo scacchistico U.S.ACLI Santa Sabina, in collaborazione con l'U.S. ACLI provinciale  e con il patrocinio e la partecipazione finanziaria del Comune di Genova - Municipio III Bassa Val Bisagno, ha organizzato il 3° torneo giovanile valido per la selezione al 27° campionato nazionale Under 16  ([classifica categorie Pulcini e Piccoli alfieri](https://santasabina.altervista.org/images/tornei/2014/2014_3_giov_u16/classifica/pulcini_alfieri/rankingagegroup.html), [classifica categorie Allievi, Cadetti e Giovanissimi](https://santasabina.altervista.org/images/tornei/2014/2014_3_giov_u16/classifica/allievi_cadetti_giov/rankingagegroup.html), [fotografie](https://santasabina.altervista.org/index.php/fotografie/category/44-3-torneo-giovanile-under-16), [bando](https://santasabina.altervista.org/images/tornei/2014/2014_3_giov_u16/2014_3_giov_u16_bando.pdf), [iscrizione e preiscrizione](https://santasabina.altervista.org/images/tornei/2014/2014_3_giov_u16/2014_3_giov_u16_iscrizione.pdf))",
  "rawHtml": "\n\t\t<div class=\"my_box_article\"><img src=\"/images/documenti/torneo_giovani.png\" border=\"0\" width=\"80\" height=\"50\" style=\"margin-right: 20px; float: left;\">\n<div class=\"my_normal\">Domenica 6 aprile, il Circolo scacchistico U.S.ACLI Santa Sabina, in collaborazione con l'U.S. ACLI provinciale &nbsp;e con il patrocinio e la partecipazione finanziaria del Comune di Genova - Municipio III Bassa Val Bisagno, ha organizzato il 3° torneo giovanile valido per la selezione al&nbsp;27° campionato nazionale Under 16&nbsp;&nbsp;<span style=\"line-height: 1.3em;\">(</span><span style=\"line-height: 1.3em;\"><span><a href=\"/images/tornei/2014/2014_3_giov_u16/classifica/pulcini_alfieri/rankingagegroup.html\" target=\"_blank\">classifica categorie Pulcini e Piccoli alfieri</a></span><span>,&nbsp;</span><a href=\"/images/tornei/2014/2014_3_giov_u16/classifica/allievi_cadetti_giov/rankingagegroup.html\" target=\"_blank\">classifica categorie Allievi, Cadetti e Giovanissimi</a>, <a href=\"/index.php/fotografie/category/44-3-torneo-giovanile-under-16\">fotografie</a>, <a href=\"/images/tornei/2014/2014_3_giov_u16/2014_3_giov_u16_bando.pdf\" target=\"_blank\">bando</a><span>,&nbsp;</span><a href=\"/images/tornei/2014/2014_3_giov_u16/2014_3_giov_u16_iscrizione.pdf\" target=\"_blank\">iscrizione e preiscrizione</a><span>)</span></span></div>\n</div> \t"
}